sqlalchemy_dbml/__init__.py
sqlalchemy_dbml/generate_dbml.py
sqlalchemy_dbml/importer.py
sqlalchemy_dbml/main.py
sqlalchemy_dbml/py.typed
sqlalchemy_dbml-0.1.0.dist-info/entry_points.txt
sqlalchemy_dbml-0.1.0.dist-info/LICENSE
sqlalchemy_dbml-0.1.0.dist-info/WHEEL
sqlalchemy_dbml-0.1.0.dist-info/METADATA
sqlalchemy_dbml-0.1.0.dist-info/RECORD
