Metadata-Version: 2.1
Name: sqlalchemy-dbml
Version: 0.1.0
Summary: Convert SQLAlchemy/SQLModel into DBML, and the other way around! 🎉
Home-page: https://github.com/Kludex/sqlalchemy-dbml
License: MIT
Author: Marcelo Trylesinski
Author-email: marcelotryle@gmail.com
Requires-Python: >=3.8,<4.0
Classifier: Intended Audience :: Developers
Classifier: License :: OSI Approved :: MIT License
Classifier: Operating System :: OS Independent
Classifier: Programming Language :: Python
Classifier: Programming Language :: Python :: 3
Classifier: Programming Language :: Python :: 3 :: Only
Classifier: Programming Language :: Python :: 3.10
Classifier: Programming Language :: Python :: 3.8
Classifier: Programming Language :: Python :: 3.9
Classifier: Topic :: Software Development :: Libraries :: Python Modules
Requires-Dist: SQLAlchemy (>=1.4.27,<2.0.0)
Requires-Dist: rich (>=10.15.0,<11.0.0)
Requires-Dist: sqlmodel (>=0.0.4,<0.0.5)
Requires-Dist: typer (>=0.4.0,<0.5.0)
Project-URL: Repository, https://github.com/Kludex/sqlalchemy-dbml
